[{"word": "1040", "bounding_box": [47.0, 37.0, 115.0, 62.0]}, {"word": "Depment f the Tresurynmal Renue Senvice", "bounding_box": [120.0, 37.0, 299.0, 53.0]}, {"word": "U.s.Individual Income Tax Return", "bounding_box": [119.0, 47.0, 342.0, 69.0]}, {"word": "OMB No.1545-0074", "bounding_box": [428.0, 57.0, 514.0, 70.0]}, {"word": "IRS U OnyDo not wie or staple in this spae", "bounding_box": [519.0, 58.0, 687.0, 74.0]}, {"word": "Filing Status Single Married fiing jointly", "bounding_box": [46.0, 70.0, 282.0, 90.0]}, {"word": "Check only", "bounding_box": [45.0, 84.0, 98.0, 100.0]}, {"word": "Married filing separatelyMFS", "bounding_box": [277.0, 75.0, 430.0, 92.0]}, {"word": "Head of householdHOH", "bounding_box": [434.0, 78.0, 564.0, 93.0]}, {"word": "Qualifying surviving", "bounding_box": [557.0, 80.0, 668.0, 96.0]}, {"word": "one box.", "bounding_box": [45.0, 98.0, 87.0, 109.0]}, {"word": "If you checked the MFS box,enter the name of your spouse If you checked the HOH or QSS box,enter the child's name if the qualifying", "bounding_box": [116.0, 96.0, 695.0, 119.0]}, {"word": "spouse (QSS)", "bounding_box": [582.0, 94.0, 642.0, 105.0]}, {"word": "person is a child but not your dependent:", "bounding_box": [115.0, 109.0, 293.0, 125.0]}, {"word": "Your first name and middle initial", "bounding_box": [47.0, 123.0, 177.0, 139.0]}, {"word": "Victoria", "bounding_box": [45.0, 135.0, 83.0, 152.0]}, {"word": "Last name", "bounding_box": [291.0, 127.0, 335.0, 141.0]}, {"word": "Koch", "bounding_box": [288.0, 138.0, 318.0, 156.0]}, {"word": "Your social security number", "bounding_box": [567.0, 132.0, 684.0, 147.0]}, {"word": "318-85.65", "bounding_box": [566.0, 144.0, 693.0, 160.0]}, {"word": "Last name", "bounding_box": [289.0, 154.0, 335.0, 170.0]}, {"word": "Spouses social security number", "bounding_box": [566.0, 160.0, 696.0, 175.0]}, {"word": "Home address (number and stretj.If you have a P.O.boxsee instructions.", "bounding_box": [46.0, 180.0, 336.0, 199.0]}, {"word": "221.7128", "bounding_box": [565.0, 172.0, 693.0, 189.0]}, {"word": "033 Paul Haven Suite 312", "bounding_box": [45.0, 194.0, 162.0, 209.0]}, {"word": "Apt.no.", "bounding_box": [506.0, 190.0, 539.0, 201.0]}, {"word": "Presidential Election Campaign", "bounding_box": [565.0, 189.0, 695.0, 206.0]}, {"word": "City, town, or post office.If you have a foreign address, also complete spaces below", "bounding_box": [46.0, 209.0, 372.0, 229.0]}, {"word": "Check here if youor your", "bounding_box": [565.0, 202.0, 673.0, 218.0]}, {"word": "Brianchester", "bounding_box": [44.0, 221.0, 104.0, 238.0]}, {"word": "State", "bounding_box": [408.0, 217.0, 435.0, 228.0]}, {"word": "ZIP code", "bounding_box": [485.0, 216.0, 526.0, 230.0]}, {"word": "spousef filing ointywant $3", "bounding_box": [565.0, 213.0, 691.0, 229.0]}, {"word": "94775", "bounding_box": [509.0, 232.0, 539.0, 242.0]}, {"word": "to go to this fund. Checking a", "bounding_box": [564.0, 224.0, 690.0, 240.0]}, {"word": "Foreign country name", "bounding_box": [45.0, 237.0, 134.0, 254.0]}, {"word": "Foreign province/state/county", "bounding_box": [311.0, 242.0, 432.0, 258.0]}, {"word": "box below will not change", "bounding_box": [565.0, 234.0, 675.0, 250.0]}, {"word": "Burundi", "bounding_box": [43.0, 250.0, 83.0, 266.0]}, {"word": "Foreign postal code", "bounding_box": [487.0, 247.0, 560.0, 258.0]}, {"word": "your tax or refuind.", "bounding_box": [564.0, 245.0, 642.0, 260.0]}, {"word": "Digital", "bounding_box": [42.0, 267.0, 83.0, 284.0]}, {"word": "You", "bounding_box": [603.0, 259.0, 639.0, 273.0]}, {"word": "Spouse", "bounding_box": [644.0, 259.0, 694.0, 275.0]}, {"word": "At any time during 2022, did you:a receive (as a reward,award, or payment for property or services) orb sell,", "bounding_box": [112.0, 269.0, 595.0, 290.0]}, {"word": "Assets", "bounding_box": [42.0, 281.0, 85.0, 297.0]}, {"word": "exchange, gift, or otherwise dispose of a digital asset (or a financial interest in a digital asset (See instructions.)", "bounding_box": [111.0, 283.0, 597.0, 303.0]}, {"word": "Standard", "bounding_box": [42.0, 297.0, 99.0, 314.0]}, {"word": "Someone can claim", "bounding_box": [111.0, 299.0, 218.0, 312.0]}, {"word": "You as a dependent", "bounding_box": [211.0, 299.0, 324.0, 315.0]}, {"word": "Yes", "bounding_box": [603.0, 291.0, 638.0, 302.0]}, {"word": "No", "bounding_box": [646.0, 290.0, 676.0, 304.0]}, {"word": "Deduction", "bounding_box": [42.0, 311.0, 105.0, 326.0]}, {"word": "Your spouse as a dependent", "bounding_box": [338.0, 302.0, 480.0, 316.0]}, {"word": "Spouse itemizes on a separate retun or you were a dual-status alien", "bounding_box": [113.0, 312.0, 427.0, 331.0]}, {"word": "Age/Blindness YouWere born before January 2,1958", "bounding_box": [41.0, 331.0, 303.0, 348.0]}, {"word": "Are blind", "bounding_box": [311.0, 336.0, 369.0, 349.0]}, {"word": "Spouse:", "bounding_box": [387.0, 339.0, 433.0, 349.0]}, {"word": "Was born before January 2.1958", "bounding_box": [427.0, 337.0, 592.0, 353.0]}, {"word": "Dependents (see instructions)", "bounding_box": [41.0, 347.0, 190.0, 364.0]}, {"word": "Is blind", "bounding_box": [603.0, 339.0, 655.0, 354.0]}, {"word": "2Social security", "bounding_box": [335.0, 351.0, 407.0, 368.0]}, {"word": "1First name", "bounding_box": [112.0, 361.0, 169.0, 376.0]}, {"word": "3 Relationship", "bounding_box": [430.0, 353.0, 494.0, 369.0]}, {"word": "4Check the box if qualifies for see instructions", "bounding_box": [499.0, 353.0, 691.0, 369.0]}, {"word": "I more", "bounding_box": [40.0, 363.0, 77.0, 379.0]}, {"word": "Last name", "bounding_box": [210.0, 365.0, 253.0, 376.0]}, {"word": "number", "bounding_box": [355.0, 365.0, 389.0, 376.0]}, {"word": "to you", "bounding_box": [447.0, 365.0, 478.0, 379.0]}, {"word": "Chid tax credit", "bounding_box": [517.0, 367.0, 579.0, 383.0]}, {"word": "than four", "bounding_box": [41.0, 377.0, 83.0, 388.0]}, {"word": "Credt for ther dependers", "bounding_box": [593.0, 368.0, 693.0, 384.0]}, {"word": "dependents,", "bounding_box": [41.0, 388.0, 99.0, 399.0]}, {"word": "see instructions", "bounding_box": [40.0, 398.0, 109.0, 410.0]}, {"word": "here", "bounding_box": [40.0, 417.0, 69.0, 431.0]}, {"word": "-", "bounding_box": [542.0, 413.0, 554.0, 426.0]}, {"word": "Income", "bounding_box": [39.0, 437.0, 95.0, 454.0]}, {"word": "1a", "bounding_box": [115.0, 437.0, 127.0, 446.0]}, {"word": "Total amount from Form(s W-2, box 1 see instructions", "bounding_box": [134.0, 435.0, 378.0, 452.0]}, {"word": "b", "bounding_box": [119.0, 452.0, 127.0, 461.0]}, {"word": "Household employee wages not reported on Form(s W-2", "bounding_box": [133.0, 450.0, 385.0, 467.0]}, {"word": "1a", "bounding_box": [583.0, 443.0, 598.0, 457.0]}, {"word": "Attach Form(s", "bounding_box": [38.0, 459.0, 103.0, 474.0]}, {"word": "1b", "bounding_box": [578.0, 453.0, 601.0, 473.0]}, {"word": "W-2here.Also", "bounding_box": [38.0, 469.0, 103.0, 486.0]}, {"word": "c", "bounding_box": [120.0, 468.0, 127.0, 475.0]}, {"word": "Tip income not reported on line 1a (see instructions)", "bounding_box": [134.0, 464.0, 361.0, 481.0]}, {"word": "Medicaid waiver payments not reported on Form(s W-2 (see instructions)", "bounding_box": [133.0, 478.0, 452.0, 498.0]}, {"word": "1c", "bounding_box": [580.0, 469.0, 598.0, 488.0]}, {"word": "W-2G and", "bounding_box": [37.0, 489.0, 84.0, 505.0]}, {"word": "attach Forms", "bounding_box": [38.0, 481.0, 97.0, 494.0]}, {"word": "Taxable dependent care benefits from Form 2441, line 26", "bounding_box": [134.0, 493.0, 383.0, 511.0]}, {"word": "1d", "bounding_box": [581.0, 484.0, 598.0, 502.0]}, {"word": "1099-R if tax", "bounding_box": [39.0, 502.0, 92.0, 513.0]}, {"word": "Employer-provided adoption benefits from Form 8839, line 29", "bounding_box": [134.0, 508.0, 402.0, 525.0]}, {"word": "1e", "bounding_box": [581.0, 500.0, 595.0, 516.0]}, {"word": "was withheld", "bounding_box": [38.0, 512.0, 95.0, 522.0]}, {"word": "if you did not", "bounding_box": [37.0, 522.0, 93.0, 539.0]}, {"word": "Wages from Form 8919line 6", "bounding_box": [133.0, 521.0, 305.0, 538.0]}, {"word": "1f", "bounding_box": [582.0, 513.0, 595.0, 528.0]}, {"word": "get a Form", "bounding_box": [39.0, 536.0, 84.0, 547.0]}, {"word": "Other earned income (see instructions)", "bounding_box": [133.0, 536.0, 303.0, 552.0]}, {"word": "1g", "bounding_box": [579.0, 527.0, 596.0, 545.0]}, {"word": "W-2,see", "bounding_box": [37.0, 543.0, 78.0, 559.0]}, {"word": "n", "bounding_box": [119.0, 540.0, 126.0, 547.0]}, {"word": "Nontaxable combat pay election (see instructions", "bounding_box": [132.0, 550.0, 352.0, 568.0]}, {"word": "1h", "bounding_box": [580.0, 543.0, 595.0, 556.0]}, {"word": "instructions.", "bounding_box": [38.0, 555.0, 87.0, 568.0]}, {"word": "Add lines 1a through 1h", "bounding_box": [133.0, 565.0, 238.0, 580.0]}, {"word": "Attach Sch. B", "bounding_box": [37.0, 577.0, 94.0, 593.0]}, {"word": "2a", "bounding_box": [111.0, 580.0, 126.0, 592.0]}, {"word": "Tax-exempt interest", "bounding_box": [131.0, 579.0, 223.0, 596.0]}, {"word": "1z", "bounding_box": [581.0, 572.0, 595.0, 588.0]}, {"word": "if required", "bounding_box": [37.0, 590.0, 82.0, 606.0]}, {"word": "2a", "bounding_box": [277.0, 583.0, 293.0, 595.0]}, {"word": "b Taxable interest", "bounding_box": [399.0, 583.0, 484.0, 599.0]}, {"word": "2b", "bounding_box": [579.0, 584.0, 596.0, 602.0]}, {"word": "3a", "bounding_box": [111.0, 595.0, 125.0, 607.0]}, {"word": "Qualified dividends", "bounding_box": [132.0, 594.0, 219.0, 609.0]}, {"word": "3a", "bounding_box": [277.0, 596.0, 292.0, 610.0]}, {"word": "b Ordinary dividends", "bounding_box": [399.0, 598.0, 498.0, 614.0]}, {"word": "4a", "bounding_box": [112.0, 611.0, 124.0, 619.0]}, {"word": "IRA distributions", "bounding_box": [131.0, 606.0, 209.0, 624.0]}, {"word": "Standard", "bounding_box": [31.0, 620.0, 75.0, 637.0]}, {"word": "4a", "bounding_box": [277.0, 611.0, 292.0, 623.0]}, {"word": "b Taxable amount", "bounding_box": [399.0, 612.0, 486.0, 628.0]}, {"word": "Deduction for-", "bounding_box": [32.0, 630.0, 97.0, 647.0]}, {"word": "5a", "bounding_box": [110.0, 623.0, 124.0, 635.0]}, {"word": "Pensions and annuities", "bounding_box": [131.0, 622.0, 234.0, 638.0]}, {"word": "5a", "bounding_box": [277.0, 624.0, 292.0, 638.0]}, {"word": "b Taxable amount", "bounding_box": [398.0, 626.0, 488.0, 641.0]}, {"word": "Singe or", "bounding_box": [33.0, 642.0, 74.0, 656.0]}, {"word": "Sa", "bounding_box": [112.0, 639.0, 123.0, 648.0]}, {"word": "Social security benefits", "bounding_box": [131.0, 637.0, 235.0, 652.0]}, {"word": "6a", "bounding_box": [275.0, 638.0, 294.0, 653.0]}, {"word": "b Taxable amount.", "bounding_box": [398.0, 641.0, 489.0, 656.0]}, {"word": "Marred iling", "bounding_box": [38.0, 652.0, 88.0, 664.0]}, {"word": "If you elect to use the lump-sum election method, check here (see instructions", "bounding_box": [131.0, 651.0, 473.0, 670.0]}, {"word": "separately,", "bounding_box": [40.0, 662.0, 81.0, 672.0]}, {"word": "$12,950", "bounding_box": [38.0, 668.0, 72.0, 681.0]}, {"word": "Marrid ing", "bounding_box": [33.0, 678.0, 85.0, 693.0]}, {"word": "Other income from Schedule 1, line 10", "bounding_box": [131.0, 680.0, 301.0, 697.0]}, {"word": "7", "bounding_box": [582.0, 673.0, 591.0, 686.0]}, {"word": "Jointly or", "bounding_box": [39.0, 690.0, 70.0, 700.0]}, {"word": ":", "bounding_box": [111.0, 684.0, 116.0, 690.0]}, {"word": "Qualitying", "bounding_box": [39.0, 698.0, 75.0, 709.0]}, {"word": "9", "bounding_box": [111.0, 698.0, 116.0, 705.0]}, {"word": "Add lines 1z,2b,3b,4b,5b,6b,7,and 8.This is your total income", "bounding_box": [131.0, 695.0, 424.0, 713.0]}, {"word": "surviving spouse", "bounding_box": [39.0, 705.0, 98.0, 718.0]}, {"word": "$25,900", "bounding_box": [39.0, 713.0, 68.0, 724.0]}, {"word": "10", "bounding_box": [106.0, 711.0, 116.0, 719.0]}, {"word": "Adjustments to income from Schedule 1.line 26", "bounding_box": [130.0, 709.0, 341.0, 725.0]}, {"word": "10", "bounding_box": [576.0, 713.0, 594.0, 731.0]}, {"word": "Headof", "bounding_box": [33.0, 724.0, 70.0, 735.0]}, {"word": "11", "bounding_box": [102.0, 723.0, 116.0, 735.0]}, {"word": "Subtract line 10 from line 9.This is your adjusted gross income", "bounding_box": [130.0, 723.0, 411.0, 741.0]}, {"word": "househoid,", "bounding_box": [38.0, 733.0, 79.0, 743.0]}, {"word": "11", "bounding_box": [572.0, 724.0, 598.0, 748.0]}, {"word": "$19,400", "bounding_box": [39.0, 741.0, 70.0, 752.0]}, {"word": "12", "bounding_box": [102.0, 737.0, 117.0, 750.0]}, {"word": "Standard deduction or itemized deductions (from Schedule A)", "bounding_box": [130.0, 738.0, 411.0, 755.0]}, {"word": "f you checked", "bounding_box": [32.0, 751.0, 90.0, 764.0]}, {"word": "12", "bounding_box": [576.0, 742.0, 594.0, 760.0]}, {"word": "any box under", "bounding_box": [39.0, 762.0, 89.0, 772.0]}, {"word": "13", "bounding_box": [103.0, 753.0, 117.0, 765.0]}, {"word": "Qualified business income deduction from Form 8995 or Form 8995-A", "bounding_box": [130.0, 753.0, 435.0, 770.0]}, {"word": "13", "bounding_box": [575.0, 757.0, 594.0, 775.0]}, {"word": "Standard", "bounding_box": [37.0, 768.0, 74.0, 781.0]}, {"word": "Deauction,", "bounding_box": [37.0, 777.0, 78.0, 790.0]}, {"word": "14", "bounding_box": [103.0, 768.0, 117.0, 780.0]}, {"word": "Add lines 12and13", "bounding_box": [130.0, 768.0, 236.0, 780.0]}, {"word": "Subtract line 14 from line 11.If zero or iess,enter -0-This is your taxable income", "bounding_box": [129.0, 780.0, 487.0, 800.0]}, {"word": "14", "bounding_box": [575.0, 772.0, 594.0, 789.0]}, {"word": "see instructions.", "bounding_box": [36.0, 786.0, 96.0, 798.0]}, {"word": "15", "bounding_box": [105.0, 783.0, 115.0, 792.0]}, {"word": "15", "bounding_box": [576.0, 788.0, 594.0, 800.0]}, {"word": "For Disclosure, Privacy Act,and Paperwork Reduction Act Notice,see separate instructions.", "bounding_box": [33.0, 808.0, 407.0, 827.0]}, {"word": "Cat No.11320B", "bounding_box": [481.0, 814.0, 541.0, 830.0]}, {"word": "Fom 10402022", "bounding_box": [613.0, 815.0, 685.0, 832.0]}]