[{"word": "SEEEEY", "bounding_box": [72.0, 67.0, 111.0, 78.0]}, {"word": "CHAMP S/L", "bounding_box": [263.0, 100.0, 323.0, 117.0]}, {"word": "TRIAL SPECIFICATION", "bounding_box": [231.0, 116.0, 353.0, 131.0]}, {"word": "CIGARETTE MAKING", "bounding_box": [72.0, 141.0, 174.0, 153.0]}, {"word": "LIMT", "bounding_box": [393.0, 152.0, 422.0, 166.0]}, {"word": "Physical Characteristics", "bounding_box": [72.0, 165.0, 222.0, 178.0]}, {"word": "Suggestion", "bounding_box": [374.0, 164.0, 440.0, 180.0]}, {"word": "HK Trial", "bounding_box": [485.0, 163.0, 539.0, 180.0]}, {"word": "Overall Cigarette Length", "bounding_box": [72.0, 190.0, 221.0, 203.0]}, {"word": "99", "bounding_box": [391.0, 188.0, 410.0, 204.0]}, {"word": "mat", "bounding_box": [423.0, 192.0, 441.0, 205.0]}, {"word": "99", "bounding_box": [487.0, 190.0, 510.0, 205.0]}, {"word": "mn", "bounding_box": [519.0, 189.0, 540.0, 205.0]}, {"word": "Tebacco Rod Length", "bounding_box": [69.0, 213.0, 185.0, 229.0]}, {"word": "72", "bounding_box": [395.0, 218.0, 408.0, 227.0]}, {"word": "72", "bounding_box": [487.0, 216.0, 514.0, 232.0]}, {"word": "ne", "bounding_box": [523.0, 218.0, 539.0, 231.0]}, {"word": "Filter Plug Length", "bounding_box": [70.0, 239.0, 185.0, 252.0]}, {"word": "27", "bounding_box": [393.0, 241.0, 412.0, 253.0]}, {"word": "27", "bounding_box": [487.0, 240.0, 511.0, 256.0]}, {"word": "an", "bounding_box": [517.0, 239.0, 542.0, 257.0]}, {"word": "Filter Plug Pressure Drop (unencap.)", "bounding_box": [69.0, 263.0, 296.0, 278.0]}, {"word": "mm", "bounding_box": [424.0, 267.0, 441.0, 280.0]}, {"word": "62", "bounding_box": [487.0, 264.0, 511.0, 280.0]}, {"word": "am", "bounding_box": [518.0, 266.0, 541.0, 280.0]}, {"word": "Filter Plug Pressure Drop encap.)", "bounding_box": [69.0, 288.0, 284.0, 303.0]}, {"word": "58.5mm", "bounding_box": [386.0, 290.0, 441.0, 304.0]}, {"word": "58.5.mm", "bounding_box": [486.0, 291.0, 540.0, 305.0]}, {"word": "Cigarette Circwaference", "bounding_box": [70.0, 315.0, 216.0, 328.0]}, {"word": "24.8.mm", "bounding_box": [484.0, 306.0, 543.0, 331.0]}, {"word": "Total Prossure Drop unencap.)", "bounding_box": [68.0, 338.0, 258.0, 353.0]}, {"word": "ma", "bounding_box": [426.0, 344.0, 439.0, 353.0]}, {"word": "am", "bounding_box": [526.0, 344.0, 538.0, 352.0]}, {"word": "Total Pressure Drop (encap.)", "bounding_box": [69.0, 365.0, 246.0, 378.0]}, {"word": "Tipping Length", "bounding_box": [67.0, 389.0, 159.0, 404.0]}, {"word": "32", "bounding_box": [383.0, 388.0, 403.0, 405.0]}, {"word": "ma", "bounding_box": [424.0, 393.0, 440.0, 406.0]}, {"word": "Print Position from filter end", "bounding_box": [69.0, 416.0, 270.0, 428.0]}, {"word": "35", "bounding_box": [377.0, 415.0, 407.0, 430.0]}, {"word": "mm", "bounding_box": [421.0, 418.0, 440.0, 429.0]}, {"word": "35", "bounding_box": [489.0, 416.0, 522.0, 430.0]}, {"word": "mm", "bounding_box": [517.0, 415.0, 540.0, 431.0]}, {"word": "Moisture Content Packing)", "bounding_box": [67.0, 438.0, 232.0, 454.0]}, {"word": "13", "bounding_box": [382.0, 439.0, 417.0, 454.0]}, {"word": "%", "bounding_box": [424.0, 441.0, 439.0, 454.0]}, {"word": "133", "bounding_box": [487.0, 438.0, 535.0, 458.0]}, {"word": "Pilter Ventilation Rate", "bounding_box": [67.0, 463.0, 215.0, 479.0]}, {"word": "Weights", "bounding_box": [65.0, 488.0, 116.0, 506.0]}, {"word": "Total Cigarette Weight", "bounding_box": [66.0, 515.0, 207.0, 529.0]}, {"word": "\"ng", "bounding_box": [416.0, 514.0, 444.0, 534.0]}, {"word": "ng.", "bounding_box": [520.0, 515.0, 546.0, 534.0]}, {"word": "Net Net Tobacco", "bounding_box": [67.0, 541.0, 165.0, 554.0]}, {"word": "858", "bounding_box": [377.0, 539.0, 402.0, 554.0]}, {"word": "mg", "bounding_box": [421.0, 543.0, 440.0, 556.0]}, {"word": "858ng", "bounding_box": [486.0, 537.0, 543.0, 558.0]}, {"word": "Tobacco Rod Density", "bounding_box": [66.0, 564.0, 190.0, 579.0]}, {"word": "243.6mg/cc", "bounding_box": [376.0, 564.0, 459.0, 580.0]}, {"word": "243.6mg/cc", "bounding_box": [488.0, 566.0, 557.0, 580.0]}, {"word": "Tipping and Tipping Application", "bounding_box": [68.0, 592.0, 264.0, 605.0]}, {"word": "Tipping Paper:", "bounding_box": [66.0, 614.0, 157.0, 630.0]}, {"word": "Supplier(s)", "bounding_box": [68.0, 642.0, 138.0, 653.0]}, {"word": "ECUSTA/B&W", "bounding_box": [337.0, 642.0, 401.0, 653.0]}, {"word": "ECUSTA/B W", "bounding_box": [449.0, 641.0, 525.0, 655.0]}, {"word": "Supplier Code Nos).", "bounding_box": [67.0, 666.0, 193.0, 680.0]}, {"word": "Color", "bounding_box": [65.0, 688.0, 102.0, 706.0]}, {"word": "Perforation Type  No.of lines", "bounding_box": [66.0, 715.0, 263.0, 730.0]}, {"word": "N/A", "bounding_box": [336.0, 717.0, 360.0, 734.0]}, {"word": "N/A", "bounding_box": [448.0, 717.0, 473.0, 733.0]}, {"word": "Porosity", "bounding_box": [65.0, 739.0, 120.0, 757.0]}, {"word": "Non Porous", "bounding_box": [335.0, 741.0, 403.0, 757.0]}, {"word": "Non Porous", "bounding_box": [448.0, 741.0, 515.0, 757.0]}, {"word": "Print Description", "bounding_box": [65.0, 765.0, 176.0, 781.0]}, {"word": "N/A", "bounding_box": [334.0, 765.0, 360.0, 783.0]}, {"word": "N.A", "bounding_box": [448.0, 767.0, 473.0, 784.0]}, {"word": "Bobbin Width", "bounding_box": [65.0, 786.0, 144.0, 801.0]}, {"word": "64", "bounding_box": [330.0, 781.0, 373.0, 803.0]}, {"word": "64m", "bounding_box": [447.0, 785.0, 486.0, 803.0]}, {"word": "Bobbin Length", "bounding_box": [64.0, 805.0, 149.0, 820.0]}, {"word": "2500M", "bounding_box": [335.0, 805.0, 377.0, 818.0]}, {"word": "2500M", "bounding_box": [449.0, 806.0, 490.0, 819.0]}, {"word": "Substance", "bounding_box": [64.0, 826.0, 125.0, 842.0]}, {"word": "36_cm/M2", "bounding_box": [334.0, 829.0, 389.0, 846.0]}, {"word": "36/", "bounding_box": [449.0, 831.0, 500.0, 845.0]}, {"word": "620753790", "bounding_box": [492.0, 849.0, 595.0, 869.0]}]