[{"word": "QUANTITATIVE RESEARCH", "bounding_box": [285.0, 103.0, 430.0, 120.0]}, {"word": "PROJECT NUMBER:", "bounding_box": [108.0, 170.0, 206.0, 184.0]}, {"word": "1991-18", "bounding_box": [260.0, 168.0, 307.0, 183.0]}, {"word": "B&W ORIGINATORMary D.Davis", "bounding_box": [107.0, 194.0, 307.0, 210.0]}, {"word": "TOMr.JohnnyPedersen -Gallup", "bounding_box": [106.0, 219.0, 333.0, 237.0]}, {"word": "INSTRUCTIOMS", "bounding_box": [107.0, 256.0, 189.0, 275.0]}, {"word": "1.", "bounding_box": [108.0, 286.0, 124.0, 299.0]}, {"word": "THE FOLLOWING DOCUMENT IS DIVIDEO INTO THO SECTIONS", "bounding_box": [146.0, 280.0, 474.0, 298.0]}, {"word": "SECTION ONE CONTAINS THE PROJECT DESCRIPTIONS AND SPECIFICATIONS FROM", "bounding_box": [148.0, 303.0, 587.0, 323.0]}, {"word": "B&W. ALL BIDS SHOULD BE BASED ON THE SPECIFICATIONS IN THIS DOCUMENT.", "bounding_box": [147.0, 317.0, 589.0, 337.0]}, {"word": "FAX TO THE FOLLOWING PERSON", "bounding_box": [148.0, 359.0, 327.0, 374.0]}, {"word": "MS.JACKIE KEY", "bounding_box": [344.0, 380.0, 435.0, 399.0]}, {"word": "B8", "bounding_box": [347.0, 397.0, 368.0, 409.0]}, {"word": "LOUISVILLE, KENTUCKY", "bounding_box": [344.0, 405.0, 474.0, 424.0]}, {"word": "U.S.A.", "bounding_box": [345.0, 422.0, 385.0, 435.0]}, {"word": "FAX MUMBER1-502-568-8092", "bounding_box": [346.0, 442.0, 518.0, 459.0]}, {"word": "2.", "bounding_box": [111.0, 475.0, 124.0, 488.0]}, {"word": "IN ORDER TO ALLOW US TO COMPARE BIDS, WE REQUEST THAT YOU SUBMIT A BID", "bounding_box": [150.0, 466.0, 593.0, 488.0]}, {"word": "FOR THE RESEARCH AS SPECIFIED IN SECTION ONE.", "bounding_box": [150.0, 483.0, 435.0, 500.0]}, {"word": "SUGGESTIONS FOR ALTERNATE DESIGNS FROM THE AGENCY ARE WELCOMED. HOWEVER,", "bounding_box": [150.0, 505.0, 612.0, 525.0]}, {"word": "FORM.", "bounding_box": [149.0, 535.0, 184.0, 552.0]}, {"word": "3.", "bounding_box": [112.0, 562.0, 128.0, 576.0]}, {"word": "IF YOU HAVE ANY QUESTIONS, PLEASE CONTACT THE FOLLOWING PERSON", "bounding_box": [150.0, 556.0, 550.0, 575.0]}, {"word": ".MaryD._Davis", "bounding_box": [151.0, 597.0, 251.0, 616.0]}, {"word": "FAX NUMBER1-502-568-8092", "bounding_box": [152.0, 623.0, 325.0, 637.0]}, {"word": "OTHER_INFORMATION", "bounding_box": [112.0, 660.0, 226.0, 678.0]}, {"word": "DATE REQUESTED:", "bounding_box": [114.0, 688.0, 211.0, 701.0]}, {"word": "_2/22_by_courier", "bounding_box": [306.0, 686.0, 408.0, 700.0]}, {"word": "DEADLINE FOR BID RECEIPT", "bounding_box": [113.0, 705.0, 275.0, 719.0]}, {"word": "3/1/91", "bounding_box": [306.0, 704.0, 352.0, 718.0]}, {"word": "464565018", "bounding_box": [482.0, 795.0, 585.0, 815.0]}]