[{"word": "GOVERNMENTOFINDIA", "bounding_box": [357.0, 88.0, 655.0, 120.0]}, {"word": "7N134R", "bounding_box": [283.0, 164.0, 392.0, 198.0]}, {"word": "Rajan Kumar", "bounding_box": [285.0, 199.0, 443.0, 225.0]}, {"word": "D0B26/01/1978", "bounding_box": [284.0, 227.0, 583.0, 258.0]}, {"word": "/MALE", "bounding_box": [283.0, 260.0, 407.0, 292.0]}, {"word": "974853868028", "bounding_box": [285.0, 381.0, 590.0, 416.0]}, {"word": "VID9167698039023358", "bounding_box": [284.0, 431.0, 591.0, 454.0]}, {"word": "T-33ITT3", "bounding_box": [121.0, 486.0, 758.0, 532.0]}]