[{"word": "INDIANUNION", "bounding_box": [232.0, 63.0, 460.0, 102.0]}, {"word": "OHHATTISGARH", "bounding_box": [560.0, 126.0, 580.0, 291.0]}, {"word": "MONISASIM KHAN", "bounding_box": [162.0, 144.0, 320.0, 164.0]}, {"word": "VEDASIMKHAN", "bounding_box": [293.0, 170.0, 428.0, 188.0]}, {"word": "MOROR CYCTEWHHREAR", "bounding_box": [220.0, 223.0, 439.0, 248.0]}, {"word": "LIGHT MOTDRVEHISLE", "bounding_box": [233.0, 262.0, 428.0, 290.0]}, {"word": "VALID THROUGHOUTINDIA", "bounding_box": [237.0, 335.0, 453.0, 359.0]}]