[{"word": "THEUNION OFINDIA", "bounding_box": [282.0, 2.0, 523.0, 48.0]}, {"word": "MAHARASHTRA STATE MOTOR DRIVING LICENCE", "bounding_box": [72.0, 1.0, 742.0, 97.0]}, {"word": "DO/:10-09-2018", "bounding_box": [484.0, 63.0, 684.0, 108.0]}, {"word": "FORMT", "bounding_box": [768.0, 92.0, 845.0, 121.0]}, {"word": "RULE16(2)", "bounding_box": [769.0, 106.0, 879.0, 141.0]}, {"word": "DLNOMH4320180008107", "bounding_box": [69.0, 96.0, 382.0, 152.0]}, {"word": "10-09-2018", "bounding_box": [556.0, 115.0, 690.0, 151.0]}, {"word": "ValidTill:09-09-2038(NT)", "bounding_box": [71.0, 122.0, 380.0, 178.0]}, {"word": "AUTHORISATION TO DRIVE FOLLOWING CLASS", "bounding_box": [236.0, 138.0, 696.0, 208.0]}, {"word": "OF VEHICLES THROUGHOUTINDIA", "bounding_box": [238.0, 172.0, 578.0, 228.0]}, {"word": "DOI", "bounding_box": [383.0, 210.0, 438.0, 241.0]}, {"word": "COV", "bounding_box": [258.0, 221.0, 324.0, 255.0]}, {"word": "10-09-2018", "bounding_box": [364.0, 234.0, 483.0, 269.0]}, {"word": "MCWG", "bounding_box": [255.0, 250.0, 334.0, 281.0]}, {"word": "BG:O+", "bounding_box": [536.0, 341.0, 638.0, 376.0]}, {"word": "DOB25-11-1995", "bounding_box": [273.0, 357.0, 501.0, 403.0]}, {"word": "Name", "bounding_box": [10.0, 436.0, 84.0, 461.0]}, {"word": "NEHA S DORUGADE", "bounding_box": [110.0, 407.0, 348.0, 454.0]}, {"word": "S/D/WOf.SHIVAJI S DORUGADE", "bounding_box": [14.0, 431.0, 377.0, 490.0]}, {"word": "Add:AL-5123M EKTAAPT SECTOR-17", "bounding_box": [17.0, 452.0, 432.0, 518.0]}, {"word": "NAV MUMBAI(MCORP.)", "bounding_box": [19.0, 492.0, 296.0, 542.0]}, {"word": "Signature/Thumb", "bounding_box": [709.0, 498.0, 906.0, 546.0]}, {"word": "THANE,MH", "bounding_box": [24.0, 532.0, 145.0, 565.0]}, {"word": "ion of Holder", "bounding_box": [802.0, 517.0, 947.0, 556.0]}, {"word": "PIN :400708", "bounding_box": [27.0, 557.0, 163.0, 587.0]}, {"word": "MH43", "bounding_box": [245.0, 590.0, 313.0, 607.0]}]