[{"word": "India DrivingLicence(Tamilnadu)", "bounding_box": [124.0, 17.0, 337.0, 42.0]}, {"word": "Form7", "bounding_box": [123.0, 30.0, 159.0, 48.0]}, {"word": "1X1503/2011", "bounding_box": [285.0, 40.0, 368.0, 57.0]}, {"word": "TN23Y20110001523", "bounding_box": [99.0, 63.0, 200.0, 83.0]}, {"word": "Nanie", "bounding_box": [50.0, 76.0, 81.0, 90.0]}, {"word": "PERVEAS", "bounding_box": [96.0, 76.0, 154.0, 94.0]}, {"word": "SHAFHR", "bounding_box": [95.0, 89.0, 143.0, 107.0]}, {"word": "57SOWKATHALIPETTAI", "bounding_box": [46.0, 109.0, 167.0, 130.0]}, {"word": "TIRUPATTUR TK VLRDY", "bounding_box": [46.0, 121.0, 164.0, 141.0]}, {"word": "Trarwndd", "bounding_box": [47.0, 147.0, 92.0, 158.0]}, {"word": "1207/1990", "bounding_box": [91.0, 170.0, 143.0, 187.0]}, {"word": "BO.", "bounding_box": [175.0, 177.0, 197.0, 189.0]}]