[{"word": "INCOME TAX DEPARTMENT", "bounding_box": [10.0, 4.0, 123.0, 23.0]}, {"word": "GOVT.OFINDIA", "bounding_box": [180.0, 5.0, 274.0, 24.0]}, {"word": "SURESH NELLI", "bounding_box": [16.0, 30.0, 84.0, 43.0]}, {"word": "LAKSHMANARAO NELLI", "bounding_box": [16.0, 60.0, 122.0, 73.0]}, {"word": "24/10/1992", "bounding_box": [14.0, 89.0, 66.0, 104.0]}, {"word": "nt Account Numo", "bounding_box": [46.0, 105.0, 107.0, 115.0]}, {"word": "AZHPN8387P", "bounding_box": [15.0, 119.0, 82.0, 132.0]}, {"word": "NSaM", "bounding_box": [15.0, 141.0, 81.0, 165.0]}]